chainlite/__init__.py
chainlite/chain_log_handler.py
chainlite/chat_lite_llm.py
chainlite/llm_config.py
chainlite/llm_generate.py
chainlite/llm_output.py
chainlite/load_prompt.py
chainlite/redis_cache.py
chainlite/threadsafe_dict.py
chainlite/utils.py
chainlite-0.4.4.dist-info/licenses/LICENSE
tasks/__init__.py
tasks/main.py
chainlite-0.4.4.dist-info/METADATA
chainlite-0.4.4.dist-info/WHEEL
chainlite-0.4.4.dist-info/top_level.txt
chainlite-0.4.4.dist-info/RECORD
