Metadata-Version: 2.4
Name: chainlite
Version: 0.4.4
Summary: A Python package that uses LangChain and LiteLLM to call large language model APIs easily
Home-page: https://github.com/stanford-oval/chainlite
Author: Sina Semnani
Author-email: sinaj@cs.stanford.edu
License: Apache License 2.0
Classifier: Programming Language :: Python :: 3
Classifier: License :: OSI Approved :: Apache Software License
Classifier: Operating System :: OS Independent
Requires-Python: >=3.10
License-File: LICENSE
Requires-Dist: tqdm
Requires-Dist: langchain>=0.3.18
Requires-Dist: langchain-community>=0.3
Requires-Dist: langgraph>=0.2
Requires-Dist: litellm==1.65.4.post1
Requires-Dist: numpydoc
Requires-Dist: grandalf
Requires-Dist: pydantic>=2.5
Requires-Dist: redis[hiredis]
Provides-Extra: dev
Requires-Dist: invoke; extra == "dev"
Requires-Dist: pytest; extra == "dev"
Requires-Dist: pytest-asyncio; extra == "dev"
Requires-Dist: setuptools; extra == "dev"
Requires-Dist: wheel; extra == "dev"
Requires-Dist: twine; extra == "dev"
Requires-Dist: isort; extra == "dev"
Requires-Dist: black; extra == "dev"
Requires-Dist: tuna; extra == "dev"
Dynamic: author
Dynamic: author-email
Dynamic: classifier
Dynamic: description
Dynamic: description-content-type
Dynamic: home-page
Dynamic: license
Dynamic: license-file
Dynamic: provides-extra
Dynamic: requires-dist
Dynamic: requires-python
Dynamic: summary
